cirq_ionq/__init__.py
cirq_ionq/_version.py
cirq_ionq/_version_test.py
cirq_ionq/calibration.py
cirq_ionq/calibration_test.py
cirq_ionq/conftest.py
cirq_ionq/ionq_client.py
cirq_ionq/ionq_client_test.py
cirq_ionq/ionq_devices.py
cirq_ionq/ionq_devices_test.py
cirq_ionq/ionq_exceptions.py
cirq_ionq/ionq_exceptions_test.py
cirq_ionq/ionq_gateset.py
cirq_ionq/ionq_gateset_test.py
cirq_ionq/ionq_native_gates.py
cirq_ionq/ionq_native_gates_test.py
cirq_ionq/ionq_native_target_gateset.py
cirq_ionq/ionq_native_target_gateset_test.py
cirq_ionq/job.py
cirq_ionq/job_test.py
cirq_ionq/json_resolver_cache.py
cirq_ionq/results.py
cirq_ionq/results_test.py
cirq_ionq/sampler.py
cirq_ionq/sampler_test.py
cirq_ionq/serializer.py
cirq_ionq/serializer_test.py
cirq_ionq/service.py
cirq_ionq/service_test.py
cirq_ionq/json_test_data/AriaNativeGateset.json
cirq_ionq/json_test_data/AriaNativeGateset.repr
cirq_ionq/json_test_data/ForteNativeGateset.json
cirq_ionq/json_test_data/ForteNativeGateset.repr
cirq_ionq/json_test_data/GPI2Gate.json
cirq_ionq/json_test_data/GPI2Gate.repr
cirq_ionq/json_test_data/GPIGate.json
cirq_ionq/json_test_data/GPIGate.repr
cirq_ionq/json_test_data/IonQTargetGateset.json
cirq_ionq/json_test_data/IonQTargetGateset.repr
cirq_ionq/json_test_data/MSGate.json
cirq_ionq/json_test_data/MSGate.repr
cirq_ionq/json_test_data/ZZGate.json
cirq_ionq/json_test_data/ZZGate.repr
cirq_ionq/json_test_data/__init__.py
cirq_ionq/json_test_data/spec.py
cirq_ionq-1.6.0.dist-info/licenses/LICENSE
cirq_ionq-1.6.0.dist-info/METADATA
cirq_ionq-1.6.0.dist-info/WHEEL
cirq_ionq-1.6.0.dist-info/top_level.txt
cirq_ionq-1.6.0.dist-info/RECORD
